mypalette/__init__.py
mypalette/load_palette.py
mypalette/visualize_palette.py
mypalette-1.0.1.1.dist-info/LICENSE
mypalette-1.0.1.1.dist-info/METADATA
mypalette-1.0.1.1.dist-info/WHEEL
mypalette-1.0.1.1.dist-info/top_level.txt
mypalette-1.0.1.1.dist-info/RECORD
