Metadata-Version: 2.1
Name: mypalette
Version: 1.0.1.1
Summary: Define and manage your plot colors in Python
Home-page: https://github.com/MattiaCinelli/mycolorpalette
Author: Mattia Cinelli
Author-email: 
License: MIT
Platform: UNKNOWN
Requires-Dist: numpy (>=1)
Requires-Dist: pandas (==1.1.4)
Requires-Dist: webcolors (==1.11.1)
Requires-Dist: matplotlib (==3.3.2)
